nikobusconnect/__init__.py
nikobusconnect/command_handler.py
nikobusconnect/connection.py
nikobusconnect/const.py
nikobusconnect/message_parser.py
nikobusconnect/protocol.py
nikobusconnect-0.1.2.dist-info/METADATA
nikobusconnect-0.1.2.dist-info/WHEEL
nikobusconnect-0.1.2.dist-info/top_level.txt
nikobusconnect-0.1.2.dist-info/RECORD
