Metadata-Version: 2.1
Name: nikobusconnect
Version: 0.1.2
Summary: A Python library for connecting to Nikobus systems
Home-page: https://github.com/fdebrus/nikobusconnect
Author: Frederic Debrus
Author-email: fdebrus@hotmail.com
Classifier: Development Status :: 3 - Alpha
Classifier: Intended Audience :: Developers
Classifier: Topic :: Software Development :: Libraries
Classifier: Topic :: Home Automation
Classifier: Programming Language :: Python :: 3
Classifier: License :: OSI Approved :: MIT License
Classifier: Operating System :: OS Independent
Requires-Python: >=3.7
Requires-Dist: pyserial-asyncio >=0.5
